mophidian/__init__.py
mophidian/__main__.py
mophidian/config.py
mophidian/cli/styles.py
mophidian/core/__init__.py
mophidian/core/serve.py
mophidian/core/util.py
mophidian/core/build/__init__.py
mophidian/core/build/construct.py
mophidian/core/build/context.py
mophidian/core/build/render.py
mophidian/file_system/__init__.py
mophidian/file_system/base.py
mophidian/file_system/containers.py
mophidian/file_system/files.py
mophidian/file_system/markdown_extensions.py
mophidian/presets/feed.xml
mophidian/presets/sitemap.xml
mophidian/presets/sitemapindex.xml
mophidian/presets/default/moph.yml
mophidian/presets/default/public/all.svg
mophidian/presets/default/src/components/GGIcon.phml
mophidian/presets/default/src/components/callout.phml
mophidian/presets/default/src/pages/README.mdx
mophidian/presets/default/src/pages/layout.phml
mophidian/presets/default/src/pages/Sample/README.md
mophidian-0.2.4.dist-info/METADATA
mophidian-0.2.4.dist-info/WHEEL
mophidian-0.2.4.dist-info/entry_points.txt
mophidian-0.2.4.dist-info/licenses/LICENSE
mophidian-0.2.4.dist-info/RECORD
