Metadata-Version: 2.1
Name: mophidian
Version: 0.2.4
Summary: Static websites with python
Project-URL: Homepage, https://github.com/Tired-Fox/Mophidian
Project-URL: Website, https://tired-fox.github.io/Mophidian/
Author-email: Tired Fox <zboehm104@gmail.com>
License-Expression: MIT
License-File: LICENSE
Classifier: License :: OSI Approved :: MIT License
Classifier: Operating System :: OS Independent
Classifier: Programming Language :: Python :: 3
Requires-Python: >=3.7
Requires-Dist: click
Requires-Dist: markdown
Requires-Dist: phml>=0.2.1
Requires-Dist: pygments
Requires-Dist: pymdown-extensions
Requires-Dist: python-frontmatter
Requires-Dist: saimll>=0.5.0
Requires-Dist: tcfg>=0.4.3
Requires-Dist: watchserver>=0.1.9
